xoxo/__init__.py
xoxo/__main__.py
xoxo/cli.py
xoxo/xoxo.py
xoxo-2023.10.21.dist-info/LICENSE
xoxo-2023.10.21.dist-info/METADATA
xoxo-2023.10.21.dist-info/WHEEL
xoxo-2023.10.21.dist-info/entry_points.txt
xoxo-2023.10.21.dist-info/top_level.txt
xoxo-2023.10.21.dist-info/RECORD
